Declare4Py/D4PyEventLog.py
Declare4Py/__init__.py
Declare4Py/run_log_generator.py
Declare4Py/Encodings/Aggregate.py
Declare4Py/Encodings/ComplexIndexBased.py
Declare4Py/Encodings/ComplexIndexNgram.py
Declare4Py/Encodings/Declare.py
Declare4Py/Encodings/IndexBased.py
Declare4Py/Encodings/LastState.py
Declare4Py/Encodings/Ngram.py
Declare4Py/Encodings/PreviousState.py
Declare4Py/Encodings/Static.py
Declare4Py/Encodings/__init__.py
Declare4Py/Encodings/FeatureEngineering/__init__.py
Declare4Py/Encodings/FeatureEngineering/inter_case_features.py
Declare4Py/ProcessMiningTasks/AbstractConformanceChecking.py
Declare4Py/ProcessMiningTasks/AbstractDiscovery.py
Declare4Py/ProcessMiningTasks/AbstractMonitoring.py
Declare4Py/ProcessMiningTasks/AbstractPMTask.py
Declare4Py/ProcessMiningTasks/AbstractQueryChecking.py
Declare4Py/ProcessMiningTasks/__init__.py
Declare4Py/ProcessMiningTasks/log_generator.py
Declare4Py/ProcessMiningTasks/ASPLogGeneration/__init__.py
Declare4Py/ProcessMiningTasks/ASPLogGeneration/asp_generator.py
Declare4Py/ProcessMiningTasks/ASPLogGeneration/ASPTranslator/__init__.py
Declare4Py/ProcessMiningTasks/ASPLogGeneration/ASPTranslator/asp_translator.py
Declare4Py/ProcessMiningTasks/ASPLogGeneration/ASPTranslator/declare_constraint_resolver.py
Declare4Py/ProcessMiningTasks/ASPLogGeneration/ASPUtils/__init__.py
Declare4Py/ProcessMiningTasks/ASPLogGeneration/ASPUtils/asp_encoding.py
Declare4Py/ProcessMiningTasks/ASPLogGeneration/ASPUtils/asp_result_parser.py
Declare4Py/ProcessMiningTasks/ASPLogGeneration/ASPUtils/asp_template.py
Declare4Py/ProcessMiningTasks/ASPLogGeneration/ASPUtils/distribution.py
Declare4Py/ProcessMiningTasks/ConformanceChecking/LTLAnalyzer.py
Declare4Py/ProcessMiningTasks/ConformanceChecking/MPDeclareAnalyzer.py
Declare4Py/ProcessMiningTasks/ConformanceChecking/MPDeclareResultsBrowser.py
Declare4Py/ProcessMiningTasks/ConformanceChecking/__init__.py
Declare4Py/ProcessMiningTasks/Discovery/DeclareMiner.py
declare4py-2.2.0.dist-info/METADATA
declare4py-2.2.0.dist-info/WHEEL
declare4py-2.2.0.dist-info/top_level.txt
declare4py-2.2.0.dist-info/RECORD
