Metadata-Version: 2.1
Name: declare4py
Version: 2.2.0
Summary: Python library to perform discovery, conformance checking and query checking of DECLARE constraints.
Home-page: https://github.com/ivanDonadello/Declare4Py
Author: Ivan Donadello, Fabrizio Maria Maggi, Francesco Riva
Author-email: Ivan Donadello <ivan.donadello@unibz.it>, Francesco Riva <francesco.riva@unibz.it>, Fabrizio Maria Maggi <maggi@inf.unibz.it>
Keywords: python,bpm,declare,process-mining,rule-mining,business-process-management,declarative-process-models
Classifier: Development Status :: 3 - Alpha
Classifier: Intended Audience :: Developers
Classifier: Intended Audience :: Information Technology
Classifier: Intended Audience :: Science/Research
Classifier: Programming Language :: Python :: 3
Classifier: Natural Language :: English
Classifier: Operating System :: Unix
Classifier: Operating System :: MacOS :: MacOS X
Classifier: Operating System :: Microsoft :: Windows
Requires-Python: >=3.9.7
Requires-Dist: logaut
Requires-Dist: packaging
Requires-Dist: mlxtend >=0.20.0
Requires-Dist: pm4py >=2.5.1
Requires-Dist: clingo >=5.6.2
Requires-Dist: boolean.py
Requires-Dist: pandas >=1.3.4
Requires-Dist: ltlf2dfa ==1.0.2
